estnltk/__about__.py
estnltk/__init__.py
estnltk/core.py
estnltk/disambiguator.py
estnltk/dividing.py
estnltk/names.py
estnltk/run_tests.py
estnltk/text.py
estnltk/prettyprinter/__init__.py
estnltk/prettyprinter/extractors.py
estnltk/prettyprinter/marker.py
estnltk/prettyprinter/prettyprinter.py
estnltk/prettyprinter/rules.py
estnltk/prettyprinter/templates.py
estnltk/prettyprinter/terminalprettyprinter.py
estnltk/prettyprinter/test_rules.py
estnltk/prettyprinter/values.py
estnltk/prettyprinter/tests/__init__.py
estnltk/prettyprinter/tests/test_basic_render.py
estnltk/prettyprinter/tests/test_css.py
estnltk/prettyprinter/tests/test_initialization.py
estnltk/prettyprinter/tests/test_rules_render.py
estnltk/single_layer_operations/__init__.py
estnltk/single_layer_operations/layer_positions.py
estnltk/tests/__init__.py
estnltk/tests/test_core.py
estnltk/tests/test_disambiguator.py
estnltk/tests/test_dividing.py
estnltk/tests/test_prettyprinter.py
estnltk/tests/test_single_element_positions.py
estnltk/tests/test_tagging.py
estnltk/tests/test_text.py
estnltk/tests/test_text_custom_layers.py
estnltk/tests/test_vabamorf.py
estnltk/tests/test_zipbuilder.py
estnltk/tokenizers/__init__.py
estnltk/tokenizers/word_tokenizer.py
estnltk/tokenizers/tests/__init__.py
estnltk/tokenizers/tests/test_word_tokenizer.py
estnltk/vabamorf/__init__.py
estnltk/vabamorf/_vabamorf.so
estnltk/vabamorf/morf.py
estnltk/vabamorf/vabamorf.i
estnltk/vabamorf/vabamorf.py
estnltk/vabamorf/dct/et.dct
estnltk/vabamorf/dct/et3.dct
estnltk/vabamorf/tests/__init__.py
estnltk/vabamorf/tests/test_analyze.py
estnltk/vabamorf/tests/test_disambiguate.py
estnltk/vabamorf/tests/test_multi.py
estnltk/vabamorf/tests/test_syllabify.py
estnltk/vabamorf/tests/test_synthesize.py
estnltk_1.4_light-1.0.1.dist-info/LICENSE
estnltk_1.4_light-1.0.1.dist-info/METADATA
estnltk_1.4_light-1.0.1.dist-info/WHEEL
estnltk_1.4_light-1.0.1.dist-info/top_level.txt
estnltk_1.4_light-1.0.1.dist-info/RECORD
